json_db_operator/JsonDbClassOperator.py
json_db_operator/JsonDbClassOperators.py
json_db_operator/JsonDbOperator.py
json_db_operator/MongoDbClassOperator.py
json_db_operator/MongoDbClassOperators.py
json_db_operator/MongoDbOperator.py
json_db_operator/__init__.py
json_db_operator/mongo_connect.py
json_db_operator/abstract/DbClassOperator.py
json_db_operator/abstract/DbClassOperators.py
json_db_operator/abstract/DbOperator.py
json_db_operator/abstract/__init__.py
json_db_operator-1.1.0.dist-info/LICENSE
json_db_operator-1.1.0.dist-info/METADATA
json_db_operator-1.1.0.dist-info/WHEEL
json_db_operator-1.1.0.dist-info/top_level.txt
json_db_operator-1.1.0.dist-info/RECORD
